simple_tools
tests
