Metadata-Version: 1.1
Name: simple-tools
Version: 0.2.0.post2
Summary: A collection of various snippets that come up regularly
Home-page: https://www.github.com/afriemann/simple_tools.git
Author: Aljosha Friemann
Author-email: a.friemann@automate.wtf
License: Copyright 2018 Aljosha Friemann
